autobahn_client/__init__.py
autobahn_client/client.py
autobahn_client/util.py
autobahn_client/proto/message_pb2.py
autobahn_client/proto/message_pb2.pyi
autobahn_client/proto/message_pb2_grpc.py
autobahn_client-0.1.2.dist-info/licenses/LICENSE
autobahn_client-0.1.2.dist-info/METADATA
autobahn_client-0.1.2.dist-info/WHEEL
autobahn_client-0.1.2.dist-info/top_level.txt
autobahn_client-0.1.2.dist-info/RECORD
