Metadata-Version: 2.4
Name: autobahn_client
Version: 0.1.2
Summary: Autobahn Client
Author-email: Denis Koterov <denis.koterov@gmail.com>
License: MIT
Project-URL: Homepage, https://github.com/godbriger/autobahn
Project-URL: Bug Tracker, https://github.com/godbriger/autobahn/issues
Classifier: Programming Language :: Python :: 3
Classifier: License :: OSI Approved :: MIT License
Classifier: Operating System :: OS Independent
Requires-Python: >=3.8
License-File: LICENSE
Requires-Dist: protobuf>=4.21.0
Requires-Dist: websockets>=15.0.1
Requires-Dist: asyncio>=3.4.3
Requires-Dist: numpy>=1.24.3
Dynamic: license-file
